context_cli/__init__.py
context_cli/__main__.py
context_cli/context.py
context_cli/core.py
context_cli/filter.py
context_cli/matcher.py
context_cli/util.py
tests/__init__.py
tests/test_context.py
tests/test_core.py
tests/test_filter.py
tests/test_matcher.py
tests/test_util.py
context_cli-0.0.dev4.dist-info/AUTHORS.md
context_cli-0.0.dev4.dist-info/LICENSE
context_cli-0.0.dev4.dist-info/METADATA
context_cli-0.0.dev4.dist-info/WHEEL
context_cli-0.0.dev4.dist-info/entry_points.txt
context_cli-0.0.dev4.dist-info/top_level.txt
context_cli-0.0.dev4.dist-info/RECORD
