Metadata-Version: 2.1
Name: context-cli
Version: 0.0.dev4
Summary: A cli tool to search with contexts.
Home-page: https://github.com/nicolasmesa/context-cli
Author: Nicolas Mesa
Author-email: nicolasmesa@gmail.com
License: MIT
Platform: UNKNOWN
Classifier: Programming Language :: Python :: 3.6
Classifier: License :: OSI Approved :: MIT License
Classifier: Operating System :: OS Independent
Classifier: Environment :: Console
Classifier: Intended Audience :: Developers
Classifier: Topic :: Software Development
Classifier: Topic :: System :: Networking
Classifier: Topic :: Terminals
Classifier: Topic :: Text Processing
Classifier: Topic :: Utilities
